local_deep_research-1.3.45.dist-info/METADATA
local_deep_research-1.3.45.dist-info/WHEEL
local_deep_research-1.3.45.dist-info/entry_points.txt
local_deep_research-1.3.45.dist-info/licenses/LICENSE
local_deep_research/__init__.py
local_deep_research/__version__.py
local_deep_research/advanced_search_system/__init__.py
local_deep_research/advanced_search_system/answer_decoding/__init__.py
local_deep_research/advanced_search_system/answer_decoding/browsecomp_answer_decoder.py
local_deep_research/advanced_search_system/candidate_exploration/README.md
local_deep_research/advanced_search_system/candidate_exploration/__init__.py
local_deep_research/advanced_search_system/candidate_exploration/adaptive_explorer.py
local_deep_research/advanced_search_system/candidate_exploration/base_explorer.py
local_deep_research/advanced_search_system/candidate_exploration/constraint_guided_explorer.py
local_deep_research/advanced_search_system/candidate_exploration/diversity_explorer.py
local_deep_research/advanced_search_system/candidate_exploration/parallel_explorer.py
local_deep_research/advanced_search_system/candidate_exploration/progressive_explorer.py
local_deep_research/advanced_search_system/candidates/__init__.py
local_deep_research/advanced_search_system/candidates/base_candidate.py
local_deep_research/advanced_search_system/constraint_checking/README.md
local_deep_research/advanced_search_system/constraint_checking/__init__.py
local_deep_research/advanced_search_system/constraint_checking/base_constraint_checker.py
local_deep_research/advanced_search_system/constraint_checking/constraint_checker.py
local_deep_research/advanced_search_system/constraint_checking/dual_confidence_checker.py
local_deep_research/advanced_search_system/constraint_checking/evidence_analyzer.py
local_deep_research/advanced_search_system/constraint_checking/intelligent_constraint_relaxer.py
local_deep_research/advanced_search_system/constraint_checking/rejection_engine.py
local_deep_research/advanced_search_system/constraint_checking/strict_checker.py
local_deep_research/advanced_search_system/constraint_checking/threshold_checker.py
local_deep_research-1.3.45.dist-info/RECORD
