Metadata-Version: 2.1
Name: local-deep-research
Version: 1.3.45
Summary: AI-powered research assistant with deep, iterative analysis using LLMs and web searches
Author-Email: LearningCircuit <185559241+LearningCircuit@users.noreply.github.com>, HashedViking <6432677+HashedViking@users.noreply.github.com>, djpetti <djpetti@gmail.com>
License: MIT License
Classifier: Programming Language :: Python :: 3
Classifier: License :: OSI Approved :: MIT License
Classifier: Operating System :: OS Independent
Project-URL: Homepage, https://github.com/LearningCircuit/local-deep-research
Project-URL: Bug Tracker, https://github.com/LearningCircuit/local-deep-research/issues
Requires-Python: <3.15,>=3.11
Requires-Dist: langchain~=1.2
Requires-Dist: langchain-community~=0.4
Requires-Dist: langchain-core~=1.2
Requires-Dist: langchain-ollama~=1.0
Requires-Dist: langchain-openai~=1.1
Requires-Dist: langchain-anthropic~=1.3
Requires-Dist: duckduckgo-search~=8.1
Requires-Dist: python-dateutil~=2.9
Requires-Dist: typing-extensions~=4.15
Requires-Dist: justext~=3.0
Requires-Dist: playwright~=1.57
Requires-Dist: beautifulsoup4~=4.14
Requires-Dist: flask~=3.1
Requires-Dist: werkzeug>=3.1.5
Requires-Dist: flask-cors~=6.0
Requires-Dist: flask-socketio~=5.6
Requires-Dist: sqlalchemy~=2.0
Requires-Dist: sqlalchemy-utc~=0.14
Requires-Dist: wikipedia~=1.4
Requires-Dist: arxiv~=2.3
Requires-Dist: pypdf>=6.6.2
Requires-Dist: sentence-transformers~=5.2
Requires-Dist: faiss-cpu~=1.13
Requires-Dist: pydantic~=2.12
Requires-Dist: pydantic-settings~=2.12
Requires-Dist: toml~=0.10
Requires-Dist: platformdirs~=4.5
Requires-Dist: dynaconf~=3.2
Requires-Dist: requests~=2.32
Requires-Dist: urllib3>=2.6.3
Requires-Dist: tiktoken~=0.12
Requires-Dist: xmltodict~=1.0
Requires-Dist: lxml~=6.0
Requires-Dist: defusedxml~=0.7
Requires-Dist: nh3~=0.3
Requires-Dist: pdfplumber~=0.11
Requires-Dist: unstructured~=0.18
Requires-Dist: google-search-results~=2.4
Requires-Dist: importlib-resources~=6.5
Requires-Dist: setuptools~=80.10
Requires-Dist: jaraco-context>=6.1.0
Requires-Dist: flask-wtf~=1.2
Requires-Dist: optuna~=4.6
Requires-Dist: elasticsearch~=9.2
Requires-Dist: methodtools~=0.4
Requires-Dist: loguru~=0.7
Requires-Dist: cachetools~=6.2
Requires-Dist: matplotlib~=3.10
Requires-Dist: pandas~=2.3
Requires-Dist: plotly~=6.5
Requires-Dist: kaleido~=1.2
Requires-Dist: aiohttp~=3.13
Requires-Dist: tenacity~=9.1
Requires-Dist: apscheduler~=3.11
Requires-Dist: rich~=14.2
Requires-Dist: click~=8.3
Requires-Dist: flask-login~=0.6
Requires-Dist: flask-limiter~=4.1
Requires-Dist: sqlcipher3-binary<0.6,>=0.5; sys_platform == "linux" and platform_machine == "x86_64"
Requires-Dist: sqlcipher3<0.6,>=0.5; (platform_machine == "aarch64" or platform_machine == "arm64") and sys_platform == "linux"
Requires-Dist: sqlcipher3<0.6,>=0.5; sys_platform != "linux"
Requires-Dist: lxml-html-clean~=0.4
Requires-Dist: weasyprint~=68.0
Requires-Dist: jaraco-context>=6.1.0
Requires-Dist: apprise~=1.9
Requires-Dist: markdown~=3.10
Requires-Dist: datasets~=4.4
Requires-Dist: pyarrow~=22.0
Requires-Dist: langchain-experimental~=0.4
Provides-Extra: vllm
Requires-Dist: torch>=2.0.0; extra == "vllm"
Requires-Dist: transformers>=4.30.0; extra == "vllm"
Requires-Dist: vllm>=0.4.0; extra == "vllm"
